isolate_cloud/__init__.py
isolate_cloud/api.py
isolate_cloud/auth/__init__.py
isolate_cloud/auth/auth0.py
isolate_cloud/auth/local.py
isolate_cloud/cli.py
isolate_cloud/flags.py
isolate_cloud/sdk.py
isolate_cloud-0.6.15.dist-info/entry_points.txt
isolate_cloud-0.6.15.dist-info/WHEEL
isolate_cloud-0.6.15.dist-info/METADATA
isolate_cloud-0.6.15.dist-info/RECORD
