Metadata-Version: 2.1
Name: isolate-cloud
Version: 0.6.15
Summary: SDK and cli for the fal isolate Cloud service
Author: Features & Labels
Author-email: hello@fal.ai
Requires-Python: >=3.7,<4.0
Classifier: Programming Language :: Python :: 3
Classifier: Programming Language :: Python :: 3.7
Classifier: Programming Language :: Python :: 3.8
Classifier: Programming Language :: Python :: 3.9
Classifier: Programming Language :: Python :: 3.10
Requires-Dist: auth0-python (>=3.24.0,<4.0.0)
Requires-Dist: click (>=8.1.3,<9.0.0)
Requires-Dist: dill (==0.3.5.1)
Requires-Dist: grpcio (>=1.50.0,<2.0.0)
Requires-Dist: isolate (>=0.5.0)
Requires-Dist: isolate-proto (>=0.0.13,<0.0.14)
Requires-Dist: requests (>=2.28.1,<3.0.0)
Requires-Dist: typing-extensions (==4.4)
